vortex_auth/__init__.py
vortex_auth/auth.py
vortex_authentication-0.3.0.dist-info/METADATA
vortex_authentication-0.3.0.dist-info/WHEEL
vortex_authentication-0.3.0.dist-info/top_level.txt
vortex_authentication-0.3.0.dist-info/RECORD
