Metadata-Version: 2.2
Name: vortex_authentication
Version: 0.3.0
Requires-Dist: requests
Dynamic: requires-dist
